aquaaristonremotethermo/__init__.py
aquaaristonremotethermo/aristonaqua.py
aquaaristonremotethermo-1.0.49.dist-info/LICENSE.txt
aquaaristonremotethermo-1.0.49.dist-info/METADATA
aquaaristonremotethermo-1.0.49.dist-info/WHEEL
aquaaristonremotethermo-1.0.49.dist-info/top_level.txt
aquaaristonremotethermo-1.0.49.dist-info/RECORD
