Metadata-Version: 2.1
Name: aquaaristonremotethermo
Version: 1.0.49
Summary: Aqua Ariston NET Remotethermo integration
Home-page: https://github.com/chomupashchuk/aquaariston-remotethermo-api
Download-URL: https://pypi.org/project/aquaaristonremotethermo/
Author: Oleh Pashchuk
Author-email: chomu.nattsol@gmail.com
License: MIT
Keywords: Ariston NET,Remotethermo,Ariston
License-File: LICENSE.txt
Requires-Dist: requests
